llmhelper/__init__.py
llmhelper/base.py
llmhelper/embeddings.py
llmhelper/exceptions.py
llmhelper/llm.py
llmhelper/rerank.py
llmhelper/template.py
llmhelper/timeutils.py
llmhelper/vectorstores.py
llmhelper/extra/__init__.py
llmhelper/extra/django_vectorstore_index_model/__init__.py
llmhelper/extra/django_vectorstore_index_model/admin.py
llmhelper/extra/django_vectorstore_index_model/apps.py
llmhelper/extra/django_vectorstore_index_model/models.py
llmhelper/extra/django_vectorstore_index_model/tests.py
llmhelper/extra/django_vectorstore_index_model/views.py
llmhelper/extra/django_vectorstore_index_model/migrations/__init__.py
llmhelper/templates/chat_with_extra_data.md
llmhelper-0.5.5.dist-info/LICENSE
llmhelper-0.5.5.dist-info/METADATA
llmhelper-0.5.5.dist-info/WHEEL
llmhelper-0.5.5.dist-info/top_level.txt
llmhelper-0.5.5.dist-info/RECORD
