Metadata-Version: 2.1
Name: llmhelper
Version: 0.5.5
Summary: 大模型辅助函数库
Author: Zhou WangJie
Maintainer: Zhou WangJie
License: Apache License, Version 2.0
Keywords: llm,llmhelper
Classifier: Development Status :: 5 - Production/Stable
Classifier: Intended Audience :: Developers
Classifier: Topic :: Software Development :: Libraries :: Python Modules
Classifier: License :: OSI Approved :: Apache Software License
Classifier: Programming Language :: Python :: 3
Classifier: Programming Language :: Python :: 3 :: Only
License-File: LICENSE
Requires-Dist: openai
Requires-Dist: langchain-core
Requires-Dist: langchain-community
Requires-Dist: zenutils
Requires-Dist: requests
Requires-Dist: pydantic
Requires-Dist: PyYAML
Requires-Dist: redis
